fusou_datasets/__init__.py
fusou_datasets/query_engine.py
fusou_datasets/relationships.py
fusou_datasets/schema.py
fusou_datasets-0.1.1.dist-info/METADATA
fusou_datasets-0.1.1.dist-info/WHEEL
fusou_datasets-0.1.1.dist-info/entry_points.txt
fusou_datasets-0.1.1.dist-info/top_level.txt
fusou_datasets-0.1.1.dist-info/RECORD
