Metadata-Version: 2.4
Name: fusou-datasets
Version: 0.1.1
Summary: Secure data loader for FUSOU research datasets with Device Trust authentication
Author-email: FUSOU Team <dev@fusou.dev>
License: MIT
Project-URL: Homepage, https://github.com/tsukasa-u/FUSOU
Project-URL: Documentation, https://github.com/tsukasa-u/FUSOU/docs
Project-URL: Repository, https://github.com/tsukasa-u/FUSOU
Project-URL: Bug Tracker, https://github.com/tsukasa-u/FUSOU/issues
Keywords: fusou,datasets,avro,pandas,research,kancolle
Classifier: Development Status :: 4 - Beta
Classifier: Intended Audience :: Developers
Classifier: Intended Audience :: Science/Research
Classifier: License :: OSI Approved :: MIT License
Classifier: Operating System :: OS Independent
Classifier: Programming Language :: Python :: 3
Classifier: Programming Language :: Python :: 3.8
Classifier: Programming Language :: Python :: 3.9
Classifier: Programming Language :: Python :: 3.10
Classifier: Programming Language :: Python :: 3.11
Classifier: Programming Language :: Python :: 3.12
Classifier: Topic :: Scientific/Engineering :: Information Analysis
Requires-Python: >=3.8
Requires-Dist: requests>=2.25.0
Requires-Dist: pandas>=1.3.0
Requires-Dist: fastavro>=1.4.0
Requires-Dist: tqdm>=4.60.0
Provides-Extra: dev
Requires-Dist: pytest>=6.0; extra == "dev"
Requires-Dist: pytest-cov>=2.0; extra == "dev"
